psyplus/__init__.py
psyplus/env_var_handler.py
psyplus/field_container.py
psyplus/psyplus.py
psyplus/utils.py
psyplus/yaml_pydantic_metadata_comment_injector.py
psyplus-0.9.5.dist-info/LICENSE
psyplus-0.9.5.dist-info/METADATA
psyplus-0.9.5.dist-info/WHEEL
psyplus-0.9.5.dist-info/top_level.txt
psyplus-0.9.5.dist-info/RECORD
