Metadata-Version: 2.1
Name: psyplus
Version: 0.9.5
Summary: A helper module that builds upon pydantic-settings to generate, read and comment a config file in yaml
Author-email: Tim Bleimehl <bleimehl@helmholtz-munich.de>
License: MIT
Project-URL: Source, https://github.com/DZD-eV-Diabetes-Research/pydantic-settings-yaml-plus
Project-URL: Issues, https://github.com/DZD-eV-Diabetes-Research/pydantic-settings-yaml-plus/issues
Keywords: DZD,pydantic,pydantic-settings
Classifier: Programming Language :: Python :: 3
Classifier: Programming Language :: Python :: 3.10
Classifier: Programming Language :: Python :: 3.11
Classifier: Programming Language :: Python :: 3.12
Requires-Python: >=3.10
License-File: LICENSE
Requires-Dist: pydantic
Requires-Dist: pydantic-settings
Requires-Dist: ruamel.yaml
Requires-Dist: pyaml
